{
	"error": false,
	"version": "fourteen",
	"filename": "PixelOS_hotdog-14.0-20240521-2303.zip",
	"datetime": 1716303832,
	"size": 2248878614,
	"url": "https://master.dl.sourceforge.net/project/justpe/A14/PixelOS/7TPro/PixelOS_hotdog-14.0-20240521-2303.zip?viasf=1",
	"github_releases_url": "https://master.dl.sourceforge.net/project/justpe/A14/PixelOS/7TPro/PixelOS_hotdog-14.0-20240521-2303.zip?viasf=1",
	"filehash": "711a52a002ff09a45a8715ae08de141c",
	"id": "d0fabc0832fee780d96f5bd27a2d790c",
	"maintainers": [{
		"main_maintainer": false,
		"ci_username": "Just_Pisces",
		"name": "Just_Pisces"
	}],
	"donate_url": "https://t.me/PixelOSOfficial",
	"website_url": "https://pixelos.vercel.app/",
	"news_url": "https://t.me/PixelOSOfficial",
	"forum_url": "https://www.coolapk.com/feed/53575053?shareKey=ODVhY2U1NTQwNmVmNjVkNGFjMWI~"
}
